pepipost/__init__.py
pepipost/api_helper.py
pepipost/configuration.py
pepipost/decorators.py
pepipost/pepipost_client.py
pepipost/controllers/__init__.py
pepipost/controllers/base_controller.py
pepipost/controllers/domain_controller.py
pepipost/controllers/domain_delete_controller.py
pepipost/controllers/events_controller.py
pepipost/controllers/mail_send_controller.py
pepipost/controllers/setrecurringcreditddetails_controller.py
pepipost/controllers/stats_controller.py
pepipost/controllers/subaccounts_controller.py
pepipost/controllers/subaccounts_create_subaccount_controller.py
pepipost/controllers/subaccounts_delete_controller.py
pepipost/controllers/subaccounts_get_sub_accounts_controller.py
pepipost/controllers/subaccounts_setsubaccountcredit_controller.py
pepipost/controllers/subaccounts_update_subaccount_controller.py
pepipost/controllers/suppression_controller.py
pepipost/exceptions/__init__.py
pepipost/exceptions/api_exception.py
pepipost/http/__init__.py
pepipost/http/http_call_back.py
pepipost/http/http_client.py
pepipost/http/http_context.py
pepipost/http/http_method_enum.py
pepipost/http/http_request.py
pepipost/http/http_response.py
pepipost/http/requests_client.py
pepipost/http/auth/__init__.py
pepipost/http/auth/custom_header_auth.py
pepipost/models/__init__.py
pepipost/models/action_enum.py
pepipost/models/add_email_or_domain_to_suppression_list.py
pepipost/models/aggregated_by_enum.py
pepipost/models/attachments.py
pepipost/models/content.py
pepipost/models/create_subaccount.py
pepipost/models/delete_domain.py
pepipost/models/delete_subacoount.py
pepipost/models/domain_struct.py
pepipost/models/email_struct.py
pepipost/models/enable_or_disable_subacoount.py
pepipost/models/events_enum.py
pepipost/models/mfrom.py
pepipost/models/personalizations.py
pepipost/models/remove_email_or_domain_to_suppression_list.py
pepipost/models/send.py
pepipost/models/settings.py
pepipost/models/sort_enum.py
pepipost/models/timeperiod_enum.py
pepipost-5.0.0.dist-info/LICENSE
pepipost-5.0.0.dist-info/METADATA
pepipost-5.0.0.dist-info/WHEEL
pepipost-5.0.0.dist-info/top_level.txt
pepipost-5.0.0.dist-info/RECORD
