Metadata-Version: 2.1
Name: pepipost
Version: 5.0.0
Summary: Official Python Library by Pepipost for sending email using Web API v5
Home-page: https://pepipost.com/
Author: Vikram Sahu - DX Team, Pepipost & APIMatic
Author-email: dx@pepipost.com
License: UNKNOWN
Platform: UNKNOWN
Classifier: Programming Language :: Python :: 3
Classifier: License :: OSI Approved :: MIT License
Classifier: Operating System :: OS Independent
Requires-Dist: requests (<3.0,>=2.20.0)
Requires-Dist: jsonpickle (<2.0,>=0.7.1)
Requires-Dist: cachecontrol (<1.0,>=0.11.7)
Requires-Dist: python-dateutil (<3.0,>=2.5.3)
